{"duration": 0.020153522491455078, "input_args": {"transformer": "MinMaxScaler(copy=True, feature_range=(0, 1))", "X": "       FIELD_8_woe  FIELD_41_woe  maCv_ismiss  maCv_woe  FIELD_4_woe  \\\n0        -0.299574     -0.060438          1.0  0.174586    -0.246718   \n1        -0.299574     -0.060438          1.0  0.174586     0.006698   \n2         0.258162      0.258162          1.0  0.174586     0.006698   \n3        -0.299574     -0.230370          0.0 -3.566812     0.006698   \n4         0.003276     -0.230370          0.0 -0.079026     0.006698   \n...            ...           ...          ...       ...          ...   \n23995    -0.299574     -0.060438          1.0  0.174586     0.006698   \n23996     0.003276     -0.230370          1.0  0.174586     0.063156   \n23997    -0.299574     -0.230370          0.0 -0.079026     0.006698   \n23998     0.258162      0.258162          1.0  0.174586     0.063156   \n23999     0.258162      0.258162          1.0  0.174586     0.006698   \n\n       FIELD_49  FIELD_51_woe  FIELD_6_woe  \n0           1.0      0.214117    -0.795961  \n1           1.0      0.214117     0.041956  \n2           1.0      0.258162     0.041956  \n3           1.0     -0.268774     0.041956  \n4           1.0      0.084808     0.041956  \n...         ...           ...          ...  \n23995       1.0      0.084808     0.041956  \n23996       1.0      0.084808     0.041956  \n23997       1.0      0.084808    -0.795961  \n23998       1.0      0.258162     0.041956  \n23999       1.0      0.258162    -0.795961  \n\n[24000 rows x 8 columns]", "y": "0        0.0\n1        0.0\n2        0.0\n3        0.0\n4        0.0\n        ... \n23995    0.0\n23996    0.0\n23997    0.0\n23998    0.0\n23999    0.0\nName: label, Length: 24000, dtype: float64", "weight": "None", "message_clsname": "'Pipeline'", "message": "None", "**": "{}"}}